pygssearch/__init__.py
pygssearch/_version.py
pygssearch/cli.py
pygssearch/utility.py
pygssearch/destination/__init__.py
pygssearch/destination/writer.py
pygssearch/progress/__init__.py
pygssearch/progress/process_manager.py
pygssearch/progress/progress.py
pygssearch/progress/tdqm_progress_manager.py
pygssearch/query/__init__.py
pygssearch/query/query.py
pygssearch/source/__init__.py
pygssearch/source/download.py
pygssearch/source/source.py
pygssearch-1.2.5.dist-info/licenses/LICENCE.txt
pygssearch-1.2.5.dist-info/METADATA
pygssearch-1.2.5.dist-info/WHEEL
pygssearch-1.2.5.dist-info/entry_points.txt
pygssearch-1.2.5.dist-info/top_level.txt
pygssearch-1.2.5.dist-info/RECORD
