Metadata-Version: 2.4
Name: pygssearch
Version: 1.2.5
Summary: Python GSS search and download product library
Author: GAEL Systems
Author-email: jean-baptiste.pilorget@gael.fr
License: Gael Systems Proprietary
Classifier: Programming Language :: Python :: 3.8
Classifier: License :: Other/Proprietary License
Requires-Python: >=3.8
License-File: LICENCE.txt
Requires-Dist: drb~=2.2.2
Requires-Dist: drb-driver-odata~=1.3.3
Requires-Dist: drb-driver-http~=1.3.7
Requires-Dist: tqdm~=4.63.0
Requires-Dist: peewee~=3.14.10
Requires-Dist: geojson~=3.1.0
Requires-Dist: requests
Requires-Dist: click
Requires-Dist: snakeviz
Requires-Dist: requests[socks]
Dynamic: license-file
